edg/__init__.py
edg/agent.py
edg/training/__init__.py
edg/utils/__init__.py
edg/utils/agent_utils.py
edg/utils/utils.py
edg/utils/vizu_utils.py
narya-1.0.0.dist-info/LICENSE
narya-1.0.0.dist-info/METADATA
narya-1.0.0.dist-info/WHEEL
narya-1.0.0.dist-info/top_level.txt
narya-1.0.0.dist-info/RECORD
