Metadata-Version: 2.1
Name: narya
Version: 1.0.0
Summary: Deep Reinforcement Learning for Real World football game, and more to come
Home-page: https://github.com/DonsetPG/narya
Author: Paul Garnier
Author-email: paul.garnier.97@gmail.com
License: MIT
Platform: UNKNOWN
Classifier: Programming Language :: Python :: 3
Classifier: License :: OSI Approved :: MIT License
Classifier: Operating System :: OS Independent
Requires-Dist: numpy (>=1.9.1)
Requires-Dist: scipy (>=0.14)
Requires-Dist: six (>=1.9.0)
Requires-Dist: gfootball
Requires-Dist: matplotlib
Requires-Dist: shapely
Requires-Dist: moviepy
Requires-Dist: pandas
Requires-Dist: pickle
